[{"habilitaciones": ["20236149"], "roles": ["fiscal", "usuario"], "name": "32801480"}, {"habilitaciones": ["22700076", "23401981", "23401555"], "roles": ["usuario", "defensa", "profesional"], "name": "10628523"}, {"habilitaciones": [], "roles": [], "name": "29037346"}, {"habilitaciones": [], "roles": [], "name": "26727211"}, {"habilitaciones": [], "roles": [], "name": "27750878"}, {"habilitaciones": ["27708049", "13988121", "30809014", "27977628", "32801480", "29037346", "14281890", "25576792", "33345332", "31779593", "13733899", "28055165", "23338233", "26681913", "20843414", "26909918", "22453683", "16581959"], "roles": ["fiscal", "usuario"], "name": "14388320"}, {"habilitaciones": [], "roles": [], "name": "30596857"}, {"habilitaciones": [], "roles": [], "name": "14723903"}, {"habilitaciones": [], "roles": [], "name": "22934745"}, {"habilitaciones": [], "roles": [], "name": "14281890"}, {"habilitaciones": [], "roles": [], "name": "17250516"}, {"habilitaciones": ["16171622", "14221391", "13922641", "22934918", "26259265", "30088610", "25269852"], "roles": ["fiscal", "usuario", "profesional"], "name": "21520539"}, {"habilitaciones": ["31233706", "26344529", "30596857", "20236149", "31189148"], "roles": ["fiscal", "usuario"], "name": "12047817"}, {"habilitaciones": [], "roles": [], "name": "33345332"}, {"habilitaciones": [], "roles": [], "name": "20680147"}, {"habilitaciones": ["16171622", "13922641"], "roles": ["fiscal", "usuario"], "name": "30088610"}, {"habilitaciones": [], "roles": [], "name": "28055165"}, {"habilitaciones": [], "roles": [], "name": "22177423"}, {"habilitaciones": ["30883724", "13988121", "16581959", "14744459", "30284124"], "roles": ["fiscal", "usuario", "profesional"], "name": "20362858"}, {"habilitaciones": ["27708049", "13988121", "30809014", "27977628", "32801480", "29037346", "14744459", "22206887", "13733899", "16581959"], "roles": ["fiscal", "usuario", "profesional"], "name": "20541909"}, {"habilitaciones": [], "roles": [], "name": "20381928"}, {"habilitaciones": [], "roles": [], "name": "30191782"}, {"habilitaciones": [], "roles": [], "name": "26121890"}, {"habilitaciones": [], "roles": [], "name": "26344529"}, {"habilitaciones": [], "roles": [], "name": "31958937"}, {"habilitaciones": [], "roles": [], "name": "16581959"}, {"habilitaciones": [], "roles": [], "name": "13899414"}, {"habilitaciones": ["26344529", "20236149", "31189148"], "roles": ["fiscal", "usuario", "profesional"], "name": "22758104"}, {"habilitaciones": [], "roles": [], "name": "10957295"}, {"habilitaciones": [], "roles": [], "name": "7996509"}, {"habilitaciones": ["14281890"], "roles": ["fiscal", "usuario"], "name": "24133820"}, {"habilitaciones": [], "roles": [], "name": "14366327"}, {"habilitaciones": ["27750878", "13899414", "14366327", "24449198"], "roles": ["usuario", "defensa"], "name": "18538659"}, {"habilitaciones": ["30883724", "30284124"], "roles": ["fiscal", "usuario"], "name": "14744459"}, {"habilitaciones": ["16171622", "13922641"], "roles": ["fiscal", "usuario"], "name": "22934918"}, {"habilitaciones": [], "roles": [], "name": "28509688"}, {"habilitaciones": [], "roles": [], "name": "17082402"}, {"habilitaciones": [], "roles": [], "name": "18560287"}, {"habilitaciones": ["27708049", "32801480", "27977628", "29037346", "14744459", "22206887", "13733899", "21520888", "16421414", "14388320", "29034363", "20541909", "17558117", "20765327"], "roles": ["fiscal", "usuario", "profesional"], "name": "17486402"}, {"habilitaciones": [], "roles": [], "name": "26856779"}, {"habilitaciones": [], "roles": [], "name": "17536123"}, {"habilitaciones": [], "roles": [], "name": "6151886"}, {"habilitaciones": [], "roles": [], "name": "14148200"}, {"habilitaciones": [], "roles": [], "name": "16164278"}, {"habilitaciones": [], "roles": [], "name": "31700094"}, {"habilitaciones": [], "roles": [], "name": "12276333"}, {"habilitaciones": [], "roles": [], "name": "11073645"}, {"habilitaciones": ["27750878", "13899414", "14366327", "24449198"], "roles": ["usuario", "defensa"], "name": "17130846"}, {"habilitaciones": [], "roles": [], "name": "30284124"}, {"habilitaciones": [], "roles": [], "name": "18069834"}, {"habilitaciones": ["22700076", "23401555"], "roles": ["usuario", "defensa", "profesional"], "name": "23401981"}, {"habilitaciones": [], "roles": [], "name": "21354030"}, {"habilitaciones": ["13988121", "14744459", "31189148", "20236149", "26344529", "21966152", "31233706", "22758104", "30596857", "24133820", "16581959"], "roles": ["fiscal", "usuario", "profesional"], "name": "18444792"}, {"habilitaciones": [], "roles": [], "name": "17447055"}, {"habilitaciones": ["27750878", "13899414", "14366327", "24449198"], "roles": ["usuario", "defensa"], "name": "27975386"}, {"habilitaciones": [], "roles": [], "name": "32538050"}, {"habilitaciones": [], "roles": [], "name": "26681913"}, {"habilitaciones": [], "roles": [], "name": "14820422"}, {"habilitaciones": ["27750878", "13899414", "14366327", "24449198"], "roles": ["usuario", "defensa"], "name": "27643524"}, {"habilitaciones": [], "roles": [], "name": "6174404"}, {"habilitaciones": [], "roles": [], "name": "14296109"}, {"habilitaciones": ["27750878", "13899414", "14366327", "24449198"], "roles": ["usuario", "defensa"], "name": "27363269"}, {"habilitaciones": [], "roles": [], "name": "30153861"}, {"habilitaciones": [], "roles": [], "name": "17644089"}, {"habilitaciones": [], "roles": [], "name": "16284529"}, {"habilitaciones": ["27750878", "13899414", "14366327", "24449198"], "roles": ["usuario", "defensa"], "name": "17340106"}, {"habilitaciones": [], "roles": [], "name": "4438433"}, {"habilitaciones": [], "roles": [], "name": "16171622"}, {"habilitaciones": [], "roles": [], "name": "23439887"}, {"habilitaciones": [], "roles": [], "name": "16616070"}, {"habilitaciones": [], "roles": [], "name": "25167812"}, {"habilitaciones": [], "roles": [], "name": "8556247"}, {"habilitaciones": [], "roles": [], "name": "8456838"}, {"habilitaciones": [], "roles": [], "name": "13922641"}, {"habilitaciones": [], "roles": [], "name": "24709684"}, {"habilitaciones": [], "roles": [], "name": "5413960"}, {"habilitaciones": [], "roles": [], "name": "25442527"}, {"habilitaciones": [], "roles": [], "name": "22934642"}, {"habilitaciones": [], "roles": [], "name": "17184428"}, {"habilitaciones": ["26344529", "30596857", "20236149"], "roles": ["fiscal", "usuario", "profesional"], "name": "21959148"}, {"habilitaciones": ["16171622", "13922641"], "roles": ["fiscal", "usuario"], "name": "25269852"}, {"habilitaciones": ["14281890", "28055165", "25576792"], "roles": ["fiscal", "usuario"], "name": "26909918"}, {"habilitaciones": ["32538396"], "roles": ["usuario", "defensa"], "name": "28682004"}, {"habilitaciones": [], "roles": [], "name": "24449579"}, {"habilitaciones": [], "roles": [], "name": "8346252"}, {"habilitaciones": [], "roles": [], "name": "25096828"}, {"habilitaciones": ["31233706", "26344529", "30596857", "20236149", "31189148"], "roles": ["fiscal", "usuario"], "name": "27714565"}, {"habilitaciones": [], "roles": [], "name": "23063893"}, {"habilitaciones": ["27750878", "13899414", "14366327", "24449198"], "roles": ["usuario", "defensa"], "name": "26727588"}, {"habilitaciones": [], "roles": [], "name": "14835142"}, {"habilitaciones": [], "roles": [], "name": "11526831"}, {"habilitaciones": [], "roles": [], "name": "24449198"}, {"habilitaciones": [], "roles": [], "name": "27271519"}, {"habilitaciones": [], "roles": [], "name": "17406864"}, {"habilitaciones": [], "roles": [], "name": "26355556"}, {"habilitaciones": [], "roles": [], "name": "22767216"}, {"habilitaciones": ["32801480", "31779593", "13733899"], "roles": ["fiscal", "usuario"], "name": "21520888"}, {"habilitaciones": ["27750878", "13899414", "14366327", "24449198"], "roles": ["usuario", "defensa"], "name": "11187145"}, {"habilitaciones": [], "roles": [], "name": "12121212"}, {"habilitaciones": [], "roles": [], "name": "6256494"}, {"habilitaciones": [], "roles": [], "name": "4411060"}, {"habilitaciones": [], "roles": [], "name": "13988121"}, {"habilitaciones": [], "roles": [], "name": "14973040"}, {"habilitaciones": ["28054639", "21354030", "28063312"], "roles": ["usuario", "defensa"], "name": "25138771"}, {"habilitaciones": [], "roles": [], "name": "28482369"}, {"habilitaciones": [], "roles": [], "name": "7732113"}, {"habilitaciones": [], "roles": [], "name": "29645817"}, {"habilitaciones": [], "roles": [], "name": "27363742"}, {"habilitaciones": [], "roles": [], "name": "16206528"}, {"habilitaciones": ["27750878", "13899414", "14366327", "24449198"], "roles": ["usuario", "defensa"], "name": "29493817"}, {"habilitaciones": [], "roles": [], "name": "6020897"}, {"habilitaciones": ["31233706", "26344529", "30596857", "20236149", "31189148"], "roles": ["fiscal", "usuario"], "name": "21966152"}, {"habilitaciones": [], "roles": [], "name": "12538081"}, {"habilitaciones": [], "roles": [], "name": "31233706"}, {"habilitaciones": [], "roles": [], "name": "29282343"}, {"habilitaciones": [], "roles": [], "name": "27092158"}, {"habilitaciones": [], "roles": [], "name": "28490554"}, {"habilitaciones": ["32538396"], "roles": ["usuario", "defensa"], "name": "29758642"}, {"habilitaciones": [], "roles": [], "name": "28054639"}, {"habilitaciones": [], "roles": [], "name": "23338233"}, {"habilitaciones": ["27708049", "32801480", "27977628", "13733899", "29037346"], "roles": ["fiscal", "usuario"], "name": "29034363"}, {"habilitaciones": [], "roles": [], "name": "11900403"}, {"habilitaciones": ["32538396"], "roles": ["usuario", "defensa"], "name": "16922147"}, {"habilitaciones": ["32801480", "29983583", "10628523", "29037346", "26727211", "22934918", "14723903", "21520539", "26355556", "20680147", "30088610", "29493817", "20362858", "23692756", "20541909", "20381928", "30191782", "26344529", "31958937", "22758104", "10957295", "7996509", "26121890", "18538659", "14744459", "28509688", "17082402", "18560287", "17486402", "26856779", "6151886", "14148200", "17536123", "31700094", "12276333", "11073645", "17130846", "16922147", "13733899", "23401981", "18444792", "26259265", "17447103", "17447055", "27975386", "32538050", "27643524", "6174404", "14296109", "27363269", "30153861", "17644089", "16284529", "24133820", "17340106", "4438433", "16171622", "23439887", "16616070", "25167812", "8556247", "8456838", "24709684", "5413960", "25442527", "27271519", "22934642", "17184428", "16164278", "25269852", "26909918", "28682004", "24449579", "8346252", "25096828", "27714565", "23063893", "26727588", "26681913", "14835142", "25442317", "17406864", "22767216", "21520888", "11187145", "12121212", "6256494", "4411060", "25138771", "28482369", "7732113", "29645817", "27363742", "16206528", "25901447", "18069834", "6020897", "12538081", "31233706", "29282343", "28490554", "29758642", "14388320", "30596857", "29034363", "23401688", "22934745", "11900403", "20765327", "21518199", "14540065", "26889441", "17558117", "16552971", "11526831", "23401555", "26067591", "14540218", "14973040", "16743010", "14221391", "21966152", "26727135", "27848200", "16841774", "23409386", "22453683", "17247197", "16159193", "21661112", "24880874", "31189148", "32429446", "10854618", "20848806", "17250516", "13733670", "22177423", "14281574", "26675621", "17536238", "13160538", "22206887", "21959148", "26047924", "16421414", "18544637", "27092628", "27708049", "27092158", "12047817", "20236149", "26736993", "10320634"], "roles": ["oficina"], "name": "Trelew"}, {"habilitaciones": [], "roles": [], "name": "23692756"}, {"habilitaciones": ["27708049", "13988121", "30809014", "27977628", "32801480", "29037346", "14744459", "13733899", "21520888", "16581959"], "roles": ["fiscal", "usuario", "profesional"], "name": "20765327"}, {"habilitaciones": [], "roles": [], "name": "21518199"}, {"habilitaciones": [], "roles": [], "name": "14540065"}, {"habilitaciones": [], "roles": [], "name": "13733899"}, {"habilitaciones": [], "roles": [], "name": "22700076"}, {"habilitaciones": [], "roles": [], "name": "26889441"}, {"habilitaciones": ["27708049", "13988121", "30809014", "27977628", "32801480", "29037346", "14744459", "14281890", "13733899", "29034363", "16581959"], "roles": ["fiscal", "usuario", "profesional"], "name": "17558117"}, {"habilitaciones": [], "roles": [], "name": "16552971"}, {"habilitaciones": ["22700076", "23401981", "24974784"], "roles": ["usuario", "defensa", "profesional"], "name": "23401555"}, {"habilitaciones": [], "roles": [], "name": "26067591"}, {"habilitaciones": ["27750878", "13899414", "14366327", "24449198"], "roles": ["usuario", "defensa"], "name": "14540218"}, {"habilitaciones": [], "roles": [], "name": "16743010"}, {"habilitaciones": ["16171622", "21520539", "13922641", "26259265", "30088610", "25269852"], "roles": ["fiscal", "usuario", "profesional"], "name": "14221391"}, {"habilitaciones": [], "roles": [], "name": "26727135"}, {"habilitaciones": [], "roles": [], "name": "25901447"}, {"habilitaciones": [], "roles": [], "name": "31779593"}, {"habilitaciones": [], "roles": [], "name": "27848200"}, {"habilitaciones": [], "roles": [], "name": "16841774"}, {"habilitaciones": [], "roles": [], "name": "20843414"}, {"habilitaciones": ["14281890", "25576792", "33345332", "28055165", "23338233", "26681913", "20843414"], "roles": ["fiscal", "usuario"], "name": "22453683"}, {"habilitaciones": ["14820422"], "roles": ["usuario"], "name": "17247197"}, {"habilitaciones": [], "roles": [], "name": "16159193"}, {"habilitaciones": [], "roles": [], "name": "21661112"}, {"habilitaciones": ["32538396"], "roles": ["usuario", "defensa"], "name": "24880874"}, {"habilitaciones": [], "roles": [], "name": "28063312"}, {"habilitaciones": [], "roles": [], "name": "23409386"}, {"habilitaciones": [], "roles": [], "name": "32429446"}, {"habilitaciones": [], "roles": [], "name": "10854618"}, {"habilitaciones": ["32538396"], "roles": ["usuario", "defensa"], "name": "20848806"}, {"habilitaciones": ["28054639", "21354030", "28063312"], "roles": ["usuario", "defensa"], "name": "13733670"}, {"habilitaciones": [], "roles": [], "name": "14281574"}, {"habilitaciones": [], "roles": [], "name": "26675621"}, {"habilitaciones": [], "roles": [], "name": "32538396"}, {"habilitaciones": [], "roles": [], "name": "17536238"}, {"habilitaciones": [], "roles": [], "name": "30809014"}, {"habilitaciones": [], "roles": [], "name": "29983583"}, {"habilitaciones": [], "roles": [], "name": "13160538"}, {"habilitaciones": ["27708049", "27977628", "13733899"], "roles": ["fiscal", "usuario"], "name": "22206887"}, {"habilitaciones": [], "roles": [], "name": "25576792"}, {"habilitaciones": [], "roles": [], "name": "17447103"}, {"habilitaciones": [], "roles": [], "name": "26047924"}, {"habilitaciones": ["27708049", "13988121", "30809014", "27977628", "32801480", "29037346", "14744459", "17486402", "13733899", "16581959"], "roles": ["fiscal", "usuario", "profesional"], "name": "16421414"}, {"habilitaciones": [], "roles": [], "name": "18544637"}, {"habilitaciones": [], "roles": [], "name": "30883724"}, {"habilitaciones": [], "roles": [], "name": "27092628"}, {"habilitaciones": [], "roles": [], "name": "27708049"}, {"habilitaciones": [], "roles": [], "name": "27977628"}, {"habilitaciones": ["16171622", "14221391", "21520539", "13922641", "22934918", "25269852"], "roles": ["fiscal", "usuario", "profesional"], "name": "26259265"}, {"habilitaciones": [], "roles": [], "name": "20236149"}, {"habilitaciones": ["27750878", "13899414", "14366327", "24449198"], "roles": ["usuario", "defensa"], "name": "25442317"}, {"habilitaciones": [], "roles": [], "name": "31189148"}, {"habilitaciones": ["13988121", "12047817", "14744459", "31189148", "20236149", "26344529", "27714565", "21966152", "21959148", "31233706", "30596857", "24133820", "16581959"], "roles": ["fiscal", "usuario", "profesional"], "name": "26736993"}, {"habilitaciones": [], "roles": [], "name": "23401688"}, {"habilitaciones": [], "roles": [], "name": "24974784"}, {"habilitaciones": [], "roles": [], "name": "10320634"}]